<?xml version="1.0" encoding="UTF-8"?>
<objects serializationModel="Studio.02.02.00">
	<object class="MixerMaster" id="{c4e2f9de-b7c0-4a66-9858-c0c80c1c23e4}">
		<property name="name">
			<value>Master Bus</value>
		</property>
		<relationship name="effectChain">
			<destination>{5af26a84-07ca-4225-ab2c-3c09b3e23da9}</destination>
		</relationship>
		<relationship name="panner">
			<destination>{4527b245-a97d-4fe6-b6e3-f396c255359f}</destination>
		</relationship>
		<relationship name="mixer">
			<destination>{423828e2-334c-4a1c-8483-419a40aab6ef}</destination>
		</relationship>
	</object>
	<object class="MixerBusEffectChain" id="{5af26a84-07ca-4225-ab2c-3c09b3e23da9}">
		<relationship name="effects">
			<destination>{a26019ff-3adc-4e10-aa8e-a06405e4ae70}</destination>
		</relationship>
	</object>
	<object class="MixerBusPanner" id="{4527b245-a97d-4fe6-b6e3-f396c255359f}">
		<property name="overridingOutputFormat">
			<value>2</value>
		</property>
	</object>
	<object class="MixerBusFader" id="{a26019ff-3adc-4e10-aa8e-a06405e4ae70}" />
</objects>
